djecrety/__init__.py
djecrety/utils.py
djecrety/management/__init__.py
djecrety/management/commands/__init__.py
djecrety/management/commands/djecrety.py
djecrety-1.0.17.dist-info/LICENSE
djecrety-1.0.17.dist-info/METADATA
djecrety-1.0.17.dist-info/WHEEL
djecrety-1.0.17.dist-info/top_level.txt
djecrety-1.0.17.dist-info/RECORD
