Metadata-Version: 2.1
Name: djecrety
Version: 1.0.17
Summary: Djecrety provides a command to generate a new secret key for your project and save it to `settings.py.`
Home-page: https://djecrety.ir
Author: Majid Rouhi
Author-email: mrouhi13@gmail.com
License: GNU Version 3 License
Classifier: Environment :: Console
Classifier: Framework :: Django
Classifier: Intended Audience :: Developers
Classifier: License :: OSI Approved :: GNU General Public License v3 (GPLv3)
Classifier: Operating System :: OS Independent
Classifier: Programming Language :: Python
Classifier: Topic :: Security :: Cryptography
Classifier: Topic :: Software Development :: Libraries :: Python Modules
Classifier: Topic :: Utilities
Requires-Python: >=3.6
License-File: LICENSE
Requires-Dist: Django (>=2.0)
